django_todo/__init__.py
django_todo/admin.py
django_todo/apps.py
django_todo/models.py
django_todo/serializers.py
django_todo/tests.py
django_todo/views.py
django_todo/migrations/0001_initial.py
django_todo/migrations/__init__.py
gbrown_django_todo-0.2.dist-info/licenses/LICENSE
gbrown_django_todo-0.2.dist-info/METADATA
gbrown_django_todo-0.2.dist-info/WHEEL
gbrown_django_todo-0.2.dist-info/top_level.txt
gbrown_django_todo-0.2.dist-info/RECORD
