Metadata-Version: 2.4
Name: gbrown-django-todo
Version: 0.2
Summary: A Django app to track todo items.
Author-email: Gabriel Brown <gabriel.brown.h@gmail.com>
License-Expression: BSD-3-Clause
Project-URL: Homepage, https://www.example.com/
Classifier: Environment :: Web Environment
Classifier: Framework :: Django
Classifier: Framework :: Django :: 5.2
Classifier: Intended Audience :: Developers
Classifier: Operating System :: OS Independent
Classifier: Programming Language :: Python
Classifier: Programming Language :: Python :: 3
Classifier: Programming Language :: Python :: 3 :: Only
Classifier: Programming Language :: Python :: 3.12
Classifier: Programming Language :: Python :: 3.13
Classifier: Topic :: Internet :: WWW/HTTP
Classifier: Topic :: Internet :: WWW/HTTP :: Dynamic Content
Requires-Python: >=3.12
License-File: LICENSE
Requires-Dist: django>=5.2
Dynamic: license-file
